<?xml version="1.0" encoding="UTF-8"?>
<ipxact:component xmlns:xsi="http://www.w3.org/2001/XMLSchema-instance" xmlns:ipxact="http://www.accellera.org/XMLSchema/IPXACT/1685-2022" xmlns:kactus2="http://kactus2.cs.tut.fi" xsi:schemaLocation="http://www.accellera.org/XMLSchema/IPXACT/1685-2022 http://www.accellera.org/XMLSchema/IPXACT/1685-2022/index.xsd">
	<ipxact:vendor>tuni.fi</ipxact:vendor>
	<ipxact:library>interconnect</ipxact:library>
	<ipxact:name>ICN_SS</ipxact:name>
	<ipxact:version>1.0</ipxact:version>
	<ipxact:busInterfaces>
		<ipxact:busInterface>
			<ipxact:name>APB0</ipxact:name>
			<ipxact:busType vendor="tuni.fi" library="interface" name="APB" version="1.0"/>
			<ipxact:abstractionTypes>
				<ipxact:abstractionType>
					<ipxact:abstractionRef vendor="tuni.fi" library="interface" name="APB.absDef" version="1.0"/>
					<ipxact:portMaps>
						<ipxact:portMap>
							<ipxact:logicalPort>
								<ipxact:name>PADDR</ipxact:name>
							</ipxact:logicalPort>
							<ipxact:physicalPort>
								<ipxact:name>PADDR</ipxact:name>
							</ipxact:physicalPort>
							<ipxact:isInformative>false</ipxact:isInformative>
						</ipxact:portMap>
						<ipxact:portMap>
							<ipxact:logicalPort>
								<ipxact:name>PENABLE</ipxact:name>
							</ipxact:logicalPort>
							<ipxact:physicalPort>
								<ipxact:name>PENABLE</ipxact:name>
							</ipxact:physicalPort>
							<ipxact:isInformative>false</ipxact:isInformative>
						</ipxact:portMap>
						<ipxact:portMap>
							<ipxact:logicalPort>
								<ipxact:name>PRDATA</ipxact:name>
								<ipxact:range>
									<ipxact:left>31</ipxact:left>
									<ipxact:right>0</ipxact:right>
								</ipxact:range>
							</ipxact:logicalPort>
							<ipxact:physicalPort>
								<ipxact:name>PRDATA</ipxact:name>
								<ipxact:partSelect>
									<ipxact:range>
										<ipxact:left>31</ipxact:left>
										<ipxact:right>0</ipxact:right>
									</ipxact:range>
								</ipxact:partSelect>
							</ipxact:physicalPort>
							<ipxact:isInformative>false</ipxact:isInformative>
						</ipxact:portMap>
						<ipxact:portMap>
							<ipxact:logicalPort>
								<ipxact:name>PREADY</ipxact:name>
								<ipxact:range>
									<ipxact:left>0</ipxact:left>
									<ipxact:right>0</ipxact:right>
								</ipxact:range>
							</ipxact:logicalPort>
							<ipxact:physicalPort>
								<ipxact:name>PREADY</ipxact:name>
								<ipxact:partSelect>
									<ipxact:range>
										<ipxact:left>0</ipxact:left>
										<ipxact:right>0</ipxact:right>
									</ipxact:range>
								</ipxact:partSelect>
							</ipxact:physicalPort>
							<ipxact:isInformative>false</ipxact:isInformative>
						</ipxact:portMap>
						<ipxact:portMap>
							<ipxact:logicalPort>
								<ipxact:name>PSEL</ipxact:name>
								<ipxact:range>
									<ipxact:left>0</ipxact:left>
									<ipxact:right>0</ipxact:right>
								</ipxact:range>
							</ipxact:logicalPort>
							<ipxact:physicalPort>
								<ipxact:name>PSEL</ipxact:name>
								<ipxact:partSelect>
									<ipxact:range>
										<ipxact:left>0</ipxact:left>
										<ipxact:right>0</ipxact:right>
									</ipxact:range>
								</ipxact:partSelect>
							</ipxact:physicalPort>
							<ipxact:isInformative>false</ipxact:isInformative>
						</ipxact:portMap>
						<ipxact:portMap>
							<ipxact:logicalPort>
								<ipxact:name>PSLVERR</ipxact:name>
								<ipxact:range>
									<ipxact:left>0</ipxact:left>
									<ipxact:right>0</ipxact:right>
								</ipxact:range>
							</ipxact:logicalPort>
							<ipxact:physicalPort>
								<ipxact:name>PSLVERR</ipxact:name>
								<ipxact:partSelect>
									<ipxact:range>
										<ipxact:left>0</ipxact:left>
										<ipxact:right>0</ipxact:right>
									</ipxact:range>
								</ipxact:partSelect>
							</ipxact:physicalPort>
							<ipxact:isInformative>false</ipxact:isInformative>
						</ipxact:portMap>
						<ipxact:portMap>
							<ipxact:logicalPort>
								<ipxact:name>PWDATA</ipxact:name>
							</ipxact:logicalPort>
							<ipxact:physicalPort>
								<ipxact:name>PWDATA</ipxact:name>
							</ipxact:physicalPort>
							<ipxact:isInformative>false</ipxact:isInformative>
						</ipxact:portMap>
						<ipxact:portMap>
							<ipxact:logicalPort>
								<ipxact:name>PWRITE</ipxact:name>
							</ipxact:logicalPort>
							<ipxact:physicalPort>
								<ipxact:name>PWRITE</ipxact:name>
							</ipxact:physicalPort>
							<ipxact:isInformative>false</ipxact:isInformative>
						</ipxact:portMap>
					</ipxact:portMaps>
				</ipxact:abstractionType>
			</ipxact:abstractionTypes>
			<ipxact:initiator>
				<ipxact:addressSpaceRef addressSpaceRef="interconnect">
					<ipxact:baseAddress>'h0</ipxact:baseAddress>
				</ipxact:addressSpaceRef>
			</ipxact:initiator>
		</ipxact:busInterface>
		<ipxact:busInterface>
			<ipxact:name>APB1</ipxact:name>
			<ipxact:busType vendor="tuni.fi" library="interface" name="APB" version="1.0"/>
			<ipxact:abstractionTypes>
				<ipxact:abstractionType>
					<ipxact:abstractionRef vendor="tuni.fi" library="interface" name="APB.absDef" version="1.0"/>
					<ipxact:portMaps>
						<ipxact:portMap>
							<ipxact:logicalPort>
								<ipxact:name>PADDR</ipxact:name>
							</ipxact:logicalPort>
							<ipxact:physicalPort>
								<ipxact:name>PADDR</ipxact:name>
							</ipxact:physicalPort>
							<ipxact:isInformative>false</ipxact:isInformative>
						</ipxact:portMap>
						<ipxact:portMap>
							<ipxact:logicalPort>
								<ipxact:name>PENABLE</ipxact:name>
							</ipxact:logicalPort>
							<ipxact:physicalPort>
								<ipxact:name>PENABLE</ipxact:name>
							</ipxact:physicalPort>
							<ipxact:isInformative>false</ipxact:isInformative>
						</ipxact:portMap>
						<ipxact:portMap>
							<ipxact:logicalPort>
								<ipxact:name>PRDATA</ipxact:name>
								<ipxact:range>
									<ipxact:left>31</ipxact:left>
									<ipxact:right>0</ipxact:right>
								</ipxact:range>
							</ipxact:logicalPort>
							<ipxact:physicalPort>
								<ipxact:name>PRDATA</ipxact:name>
								<ipxact:partSelect>
									<ipxact:range>
										<ipxact:left>63</ipxact:left>
										<ipxact:right>32</ipxact:right>
									</ipxact:range>
								</ipxact:partSelect>
							</ipxact:physicalPort>
							<ipxact:isInformative>false</ipxact:isInformative>
						</ipxact:portMap>
						<ipxact:portMap>
							<ipxact:logicalPort>
								<ipxact:name>PREADY</ipxact:name>
								<ipxact:range>
									<ipxact:left>0</ipxact:left>
									<ipxact:right>0</ipxact:right>
								</ipxact:range>
							</ipxact:logicalPort>
							<ipxact:physicalPort>
								<ipxact:name>PREADY</ipxact:name>
								<ipxact:partSelect>
									<ipxact:range>
										<ipxact:left>1</ipxact:left>
										<ipxact:right>1</ipxact:right>
									</ipxact:range>
								</ipxact:partSelect>
							</ipxact:physicalPort>
							<ipxact:isInformative>false</ipxact:isInformative>
						</ipxact:portMap>
						<ipxact:portMap>
							<ipxact:logicalPort>
								<ipxact:name>PSEL</ipxact:name>
								<ipxact:range>
									<ipxact:left>0</ipxact:left>
									<ipxact:right>0</ipxact:right>
								</ipxact:range>
							</ipxact:logicalPort>
							<ipxact:physicalPort>
								<ipxact:name>PSEL</ipxact:name>
								<ipxact:partSelect>
									<ipxact:range>
										<ipxact:left>1</ipxact:left>
										<ipxact:right>1</ipxact:right>
									</ipxact:range>
								</ipxact:partSelect>
							</ipxact:physicalPort>
							<ipxact:isInformative>false</ipxact:isInformative>
						</ipxact:portMap>
						<ipxact:portMap>
							<ipxact:logicalPort>
								<ipxact:name>PSLVERR</ipxact:name>
								<ipxact:range>
									<ipxact:left>0</ipxact:left>
									<ipxact:right>0</ipxact:right>
								</ipxact:range>
							</ipxact:logicalPort>
							<ipxact:physicalPort>
								<ipxact:name>PSLVERR</ipxact:name>
								<ipxact:partSelect>
									<ipxact:range>
										<ipxact:left>1</ipxact:left>
										<ipxact:right>1</ipxact:right>
									</ipxact:range>
								</ipxact:partSelect>
							</ipxact:physicalPort>
							<ipxact:isInformative>false</ipxact:isInformative>
						</ipxact:portMap>
						<ipxact:portMap>
							<ipxact:logicalPort>
								<ipxact:name>PWDATA</ipxact:name>
							</ipxact:logicalPort>
							<ipxact:physicalPort>
								<ipxact:name>PWDATA</ipxact:name>
							</ipxact:physicalPort>
							<ipxact:isInformative>false</ipxact:isInformative>
						</ipxact:portMap>
						<ipxact:portMap>
							<ipxact:logicalPort>
								<ipxact:name>PWRITE</ipxact:name>
							</ipxact:logicalPort>
							<ipxact:physicalPort>
								<ipxact:name>PWRITE</ipxact:name>
							</ipxact:physicalPort>
							<ipxact:isInformative>false</ipxact:isInformative>
						</ipxact:portMap>
					</ipxact:portMaps>
				</ipxact:abstractionType>
			</ipxact:abstractionTypes>
			<ipxact:initiator>
				<ipxact:addressSpaceRef addressSpaceRef="interconnect">
					<ipxact:baseAddress>'h100</ipxact:baseAddress>
				</ipxact:addressSpaceRef>
			</ipxact:initiator>
		</ipxact:busInterface>
		<ipxact:busInterface>
			<ipxact:name>APB2</ipxact:name>
			<ipxact:busType vendor="tuni.fi" library="interface" name="APB" version="1.0"/>
			<ipxact:abstractionTypes>
				<ipxact:abstractionType>
					<ipxact:abstractionRef vendor="tuni.fi" library="interface" name="APB.absDef" version="1.0"/>
					<ipxact:portMaps>
						<ipxact:portMap>
							<ipxact:logicalPort>
								<ipxact:name>PADDR</ipxact:name>
							</ipxact:logicalPort>
							<ipxact:physicalPort>
								<ipxact:name>PADDR</ipxact:name>
							</ipxact:physicalPort>
							<ipxact:isInformative>false</ipxact:isInformative>
						</ipxact:portMap>
						<ipxact:portMap>
							<ipxact:logicalPort>
								<ipxact:name>PENABLE</ipxact:name>
							</ipxact:logicalPort>
							<ipxact:physicalPort>
								<ipxact:name>PENABLE</ipxact:name>
							</ipxact:physicalPort>
							<ipxact:isInformative>false</ipxact:isInformative>
						</ipxact:portMap>
						<ipxact:portMap>
							<ipxact:logicalPort>
								<ipxact:name>PRDATA</ipxact:name>
								<ipxact:range>
									<ipxact:left>31</ipxact:left>
									<ipxact:right>0</ipxact:right>
								</ipxact:range>
							</ipxact:logicalPort>
							<ipxact:physicalPort>
								<ipxact:name>PRDATA</ipxact:name>
								<ipxact:partSelect>
									<ipxact:range>
										<ipxact:left>95</ipxact:left>
										<ipxact:right>64</ipxact:right>
									</ipxact:range>
								</ipxact:partSelect>
							</ipxact:physicalPort>
							<ipxact:isInformative>false</ipxact:isInformative>
						</ipxact:portMap>
						<ipxact:portMap>
							<ipxact:logicalPort>
								<ipxact:name>PREADY</ipxact:name>
								<ipxact:range>
									<ipxact:left>0</ipxact:left>
									<ipxact:right>0</ipxact:right>
								</ipxact:range>
							</ipxact:logicalPort>
							<ipxact:physicalPort>
								<ipxact:name>PREADY</ipxact:name>
								<ipxact:partSelect>
									<ipxact:range>
										<ipxact:left>2</ipxact:left>
										<ipxact:right>2</ipxact:right>
									</ipxact:range>
								</ipxact:partSelect>
							</ipxact:physicalPort>
							<ipxact:isInformative>false</ipxact:isInformative>
						</ipxact:portMap>
						<ipxact:portMap>
							<ipxact:logicalPort>
								<ipxact:name>PSEL</ipxact:name>
								<ipxact:range>
									<ipxact:left>0</ipxact:left>
									<ipxact:right>0</ipxact:right>
								</ipxact:range>
							</ipxact:logicalPort>
							<ipxact:physicalPort>
								<ipxact:name>PSEL</ipxact:name>
								<ipxact:partSelect>
									<ipxact:range>
										<ipxact:left>2</ipxact:left>
										<ipxact:right>2</ipxact:right>
									</ipxact:range>
								</ipxact:partSelect>
							</ipxact:physicalPort>
							<ipxact:isInformative>false</ipxact:isInformative>
						</ipxact:portMap>
						<ipxact:portMap>
							<ipxact:logicalPort>
								<ipxact:name>PSLVERR</ipxact:name>
								<ipxact:range>
									<ipxact:left>0</ipxact:left>
									<ipxact:right>0</ipxact:right>
								</ipxact:range>
							</ipxact:logicalPort>
							<ipxact:physicalPort>
								<ipxact:name>PSLVERR</ipxact:name>
								<ipxact:partSelect>
									<ipxact:range>
										<ipxact:left>2</ipxact:left>
										<ipxact:right>2</ipxact:right>
									</ipxact:range>
								</ipxact:partSelect>
							</ipxact:physicalPort>
							<ipxact:isInformative>false</ipxact:isInformative>
						</ipxact:portMap>
						<ipxact:portMap>
							<ipxact:logicalPort>
								<ipxact:name>PWDATA</ipxact:name>
							</ipxact:logicalPort>
							<ipxact:physicalPort>
								<ipxact:name>PWDATA</ipxact:name>
							</ipxact:physicalPort>
							<ipxact:isInformative>false</ipxact:isInformative>
						</ipxact:portMap>
						<ipxact:portMap>
							<ipxact:logicalPort>
								<ipxact:name>PWRITE</ipxact:name>
							</ipxact:logicalPort>
							<ipxact:physicalPort>
								<ipxact:name>PWRITE</ipxact:name>
							</ipxact:physicalPort>
							<ipxact:isInformative>false</ipxact:isInformative>
						</ipxact:portMap>
					</ipxact:portMaps>
				</ipxact:abstractionType>
			</ipxact:abstractionTypes>
			<ipxact:initiator>
				<ipxact:addressSpaceRef addressSpaceRef="interconnect">
					<ipxact:baseAddress>'h200</ipxact:baseAddress>
				</ipxact:addressSpaceRef>
			</ipxact:initiator>
		</ipxact:busInterface>
		<ipxact:busInterface>
			<ipxact:name>APB3</ipxact:name>
			<ipxact:busType vendor="tuni.fi" library="interface" name="APB" version="1.0"/>
			<ipxact:abstractionTypes>
				<ipxact:abstractionType>
					<ipxact:abstractionRef vendor="tuni.fi" library="interface" name="APB.absDef" version="1.0"/>
					<ipxact:portMaps>
						<ipxact:portMap>
							<ipxact:logicalPort>
								<ipxact:name>PADDR</ipxact:name>
							</ipxact:logicalPort>
							<ipxact:physicalPort>
								<ipxact:name>PADDR</ipxact:name>
							</ipxact:physicalPort>
							<ipxact:isInformative>false</ipxact:isInformative>
						</ipxact:portMap>
						<ipxact:portMap>
							<ipxact:logicalPort>
								<ipxact:name>PENABLE</ipxact:name>
							</ipxact:logicalPort>
							<ipxact:physicalPort>
								<ipxact:name>PENABLE</ipxact:name>
							</ipxact:physicalPort>
							<ipxact:isInformative>false</ipxact:isInformative>
						</ipxact:portMap>
						<ipxact:portMap>
							<ipxact:logicalPort>
								<ipxact:name>PRDATA</ipxact:name>
								<ipxact:range>
									<ipxact:left>31</ipxact:left>
									<ipxact:right>0</ipxact:right>
								</ipxact:range>
							</ipxact:logicalPort>
							<ipxact:physicalPort>
								<ipxact:name>PRDATA</ipxact:name>
								<ipxact:partSelect>
									<ipxact:range>
										<ipxact:left>127</ipxact:left>
										<ipxact:right>96</ipxact:right>
									</ipxact:range>
								</ipxact:partSelect>
							</ipxact:physicalPort>
							<ipxact:isInformative>false</ipxact:isInformative>
						</ipxact:portMap>
						<ipxact:portMap>
							<ipxact:logicalPort>
								<ipxact:name>PREADY</ipxact:name>
								<ipxact:range>
									<ipxact:left>0</ipxact:left>
									<ipxact:right>0</ipxact:right>
								</ipxact:range>
							</ipxact:logicalPort>
							<ipxact:physicalPort>
								<ipxact:name>PREADY</ipxact:name>
								<ipxact:partSelect>
									<ipxact:range>
										<ipxact:left>3</ipxact:left>
										<ipxact:right>3</ipxact:right>
									</ipxact:range>
								</ipxact:partSelect>
							</ipxact:physicalPort>
							<ipxact:isInformative>false</ipxact:isInformative>
						</ipxact:portMap>
						<ipxact:portMap>
							<ipxact:logicalPort>
								<ipxact:name>PSEL</ipxact:name>
								<ipxact:range>
									<ipxact:left>0</ipxact:left>
									<ipxact:right>0</ipxact:right>
								</ipxact:range>
							</ipxact:logicalPort>
							<ipxact:physicalPort>
								<ipxact:name>PSEL</ipxact:name>
								<ipxact:partSelect>
									<ipxact:range>
										<ipxact:left>3</ipxact:left>
										<ipxact:right>3</ipxact:right>
									</ipxact:range>
								</ipxact:partSelect>
							</ipxact:physicalPort>
							<ipxact:isInformative>false</ipxact:isInformative>
						</ipxact:portMap>
						<ipxact:portMap>
							<ipxact:logicalPort>
								<ipxact:name>PSLVERR</ipxact:name>
								<ipxact:range>
									<ipxact:left>0</ipxact:left>
									<ipxact:right>0</ipxact:right>
								</ipxact:range>
							</ipxact:logicalPort>
							<ipxact:physicalPort>
								<ipxact:name>PSLVERR</ipxact:name>
								<ipxact:partSelect>
									<ipxact:range>
										<ipxact:left>3</ipxact:left>
										<ipxact:right>3</ipxact:right>
									</ipxact:range>
								</ipxact:partSelect>
							</ipxact:physicalPort>
							<ipxact:isInformative>false</ipxact:isInformative>
						</ipxact:portMap>
						<ipxact:portMap>
							<ipxact:logicalPort>
								<ipxact:name>PWDATA</ipxact:name>
							</ipxact:logicalPort>
							<ipxact:physicalPort>
								<ipxact:name>PWDATA</ipxact:name>
							</ipxact:physicalPort>
							<ipxact:isInformative>false</ipxact:isInformative>
						</ipxact:portMap>
						<ipxact:portMap>
							<ipxact:logicalPort>
								<ipxact:name>PWRITE</ipxact:name>
							</ipxact:logicalPort>
							<ipxact:physicalPort>
								<ipxact:name>PWRITE</ipxact:name>
							</ipxact:physicalPort>
							<ipxact:isInformative>false</ipxact:isInformative>
						</ipxact:portMap>
					</ipxact:portMaps>
				</ipxact:abstractionType>
			</ipxact:abstractionTypes>
			<ipxact:initiator>
				<ipxact:addressSpaceRef addressSpaceRef="interconnect">
					<ipxact:baseAddress>'h300</ipxact:baseAddress>
				</ipxact:addressSpaceRef>
			</ipxact:initiator>
		</ipxact:busInterface>
		<ipxact:busInterface>
			<ipxact:name>Clock</ipxact:name>
			<ipxact:busType vendor="tuni.fi" library="interface" name="clock" version="1.0"/>
			<ipxact:abstractionTypes>
				<ipxact:abstractionType>
					<ipxact:abstractionRef vendor="tuni.fi" library="interface" name="clock.absDef" version="1.0"/>
					<ipxact:portMaps>
						<ipxact:portMap>
							<ipxact:logicalPort>
								<ipxact:name>clk</ipxact:name>
							</ipxact:logicalPort>
							<ipxact:physicalPort>
								<ipxact:name>clk</ipxact:name>
							</ipxact:physicalPort>
							<ipxact:isInformative>false</ipxact:isInformative>
						</ipxact:portMap>
					</ipxact:portMaps>
				</ipxact:abstractionType>
			</ipxact:abstractionTypes>
			<ipxact:target/>
		</ipxact:busInterface>
		<ipxact:busInterface>
			<ipxact:name>Reset</ipxact:name>
			<ipxact:busType vendor="tuni.fi" library="interface" name="reset" version="1.0"/>
			<ipxact:abstractionTypes>
				<ipxact:abstractionType>
					<ipxact:abstractionRef vendor="tuni.fi" library="interface" name="reset.absDef" version="1.0"/>
					<ipxact:portMaps>
						<ipxact:portMap>
							<ipxact:logicalPort>
								<ipxact:name>reset</ipxact:name>
							</ipxact:logicalPort>
							<ipxact:physicalPort>
								<ipxact:name>reset_int</ipxact:name>
							</ipxact:physicalPort>
							<ipxact:isInformative>false</ipxact:isInformative>
						</ipxact:portMap>
					</ipxact:portMaps>
				</ipxact:abstractionType>
			</ipxact:abstractionTypes>
			<ipxact:target/>
		</ipxact:busInterface>
		<ipxact:busInterface>
			<ipxact:name>SS_Ctrl</ipxact:name>
			<ipxact:busType vendor="tuni.fi" library="interface" name="SS_Ctrl" version="1.0"/>
			<ipxact:abstractionTypes>
				<ipxact:abstractionType>
					<ipxact:abstractionRef vendor="tuni.fi" library="interface" name="SS_Ctrl.absDef" version="1.0"/>
					<ipxact:portMaps>
						<ipxact:portMap>
							<ipxact:logicalPort>
								<ipxact:name>clk_ctrl</ipxact:name>
							</ipxact:logicalPort>
							<ipxact:physicalPort>
								<ipxact:name>ss_ctrl_icn</ipxact:name>
							</ipxact:physicalPort>
							<ipxact:isInformative>false</ipxact:isInformative>
						</ipxact:portMap>
					</ipxact:portMaps>
				</ipxact:abstractionType>
			</ipxact:abstractionTypes>
			<ipxact:target/>
		</ipxact:busInterface>
		<ipxact:busInterface>
			<ipxact:name>AXI4LITE_icn</ipxact:name>
			<ipxact:busType vendor="tuni.fi" library="interface" name="AXI4LITE" version="1.0"/>
			<ipxact:abstractionTypes>
				<ipxact:abstractionType>
					<ipxact:abstractionRef vendor="tuni.fi" library="interface" name="AXI4LITE.absDef" version="1.0"/>
					<ipxact:portMaps>
						<ipxact:portMap>
							<ipxact:logicalPort>
								<ipxact:name>AR_ADDR</ipxact:name>
							</ipxact:logicalPort>
							<ipxact:physicalPort>
								<ipxact:name>icn_ar_addr_in</ipxact:name>
							</ipxact:physicalPort>
							<ipxact:isInformative>false</ipxact:isInformative>
						</ipxact:portMap>
						<ipxact:portMap>
							<ipxact:logicalPort>
								<ipxact:name>AR_VALID</ipxact:name>
							</ipxact:logicalPort>
							<ipxact:physicalPort>
								<ipxact:name>icn_ar_valid_in</ipxact:name>
							</ipxact:physicalPort>
							<ipxact:isInformative>false</ipxact:isInformative>
						</ipxact:portMap>
						<ipxact:portMap>
							<ipxact:logicalPort>
								<ipxact:name>AW_ADDR</ipxact:name>
							</ipxact:logicalPort>
							<ipxact:physicalPort>
								<ipxact:name>icn_aw_addr_in</ipxact:name>
							</ipxact:physicalPort>
							<ipxact:isInformative>false</ipxact:isInformative>
						</ipxact:portMap>
						<ipxact:portMap>
							<ipxact:logicalPort>
								<ipxact:name>AW_VALID</ipxact:name>
							</ipxact:logicalPort>
							<ipxact:physicalPort>
								<ipxact:name>icn_aw_valid_in</ipxact:name>
							</ipxact:physicalPort>
							<ipxact:isInformative>false</ipxact:isInformative>
						</ipxact:portMap>
						<ipxact:portMap>
							<ipxact:logicalPort>
								<ipxact:name>B_READY</ipxact:name>
							</ipxact:logicalPort>
							<ipxact:physicalPort>
								<ipxact:name>icn_b_ready_in</ipxact:name>
							</ipxact:physicalPort>
							<ipxact:isInformative>false</ipxact:isInformative>
						</ipxact:portMap>
						<ipxact:portMap>
							<ipxact:logicalPort>
								<ipxact:name>B_RESP</ipxact:name>
							</ipxact:logicalPort>
							<ipxact:physicalPort>
								<ipxact:name>icn_b_resp_out</ipxact:name>
							</ipxact:physicalPort>
							<ipxact:isInformative>false</ipxact:isInformative>
						</ipxact:portMap>
						<ipxact:portMap>
							<ipxact:logicalPort>
								<ipxact:name>B_VALID</ipxact:name>
							</ipxact:logicalPort>
							<ipxact:physicalPort>
								<ipxact:name>icn_b_valid_out</ipxact:name>
							</ipxact:physicalPort>
							<ipxact:isInformative>false</ipxact:isInformative>
						</ipxact:portMap>
						<ipxact:portMap>
							<ipxact:logicalPort>
								<ipxact:name>R_DATA</ipxact:name>
							</ipxact:logicalPort>
							<ipxact:physicalPort>
								<ipxact:name>icn_r_data_out</ipxact:name>
							</ipxact:physicalPort>
							<ipxact:isInformative>false</ipxact:isInformative>
						</ipxact:portMap>
						<ipxact:portMap>
							<ipxact:logicalPort>
								<ipxact:name>R_READY</ipxact:name>
							</ipxact:logicalPort>
							<ipxact:physicalPort>
								<ipxact:name>icn_r_ready_in</ipxact:name>
							</ipxact:physicalPort>
							<ipxact:isInformative>false</ipxact:isInformative>
						</ipxact:portMap>
						<ipxact:portMap>
							<ipxact:logicalPort>
								<ipxact:name>R_RESP</ipxact:name>
							</ipxact:logicalPort>
							<ipxact:physicalPort>
								<ipxact:name>icn_r_resp_out</ipxact:name>
							</ipxact:physicalPort>
							<ipxact:isInformative>false</ipxact:isInformative>
						</ipxact:portMap>
						<ipxact:portMap>
							<ipxact:logicalPort>
								<ipxact:name>R_VALID</ipxact:name>
							</ipxact:logicalPort>
							<ipxact:physicalPort>
								<ipxact:name>icn_r_valid_out</ipxact:name>
							</ipxact:physicalPort>
							<ipxact:isInformative>false</ipxact:isInformative>
						</ipxact:portMap>
						<ipxact:portMap>
							<ipxact:logicalPort>
								<ipxact:name>AW_READY</ipxact:name>
							</ipxact:logicalPort>
							<ipxact:physicalPort>
								<ipxact:name>icn_aw_ready_out</ipxact:name>
							</ipxact:physicalPort>
							<ipxact:isInformative>false</ipxact:isInformative>
						</ipxact:portMap>
						<ipxact:portMap>
							<ipxact:logicalPort>
								<ipxact:name>W_DATA</ipxact:name>
							</ipxact:logicalPort>
							<ipxact:physicalPort>
								<ipxact:name>icn_w_data_in</ipxact:name>
							</ipxact:physicalPort>
							<ipxact:isInformative>false</ipxact:isInformative>
						</ipxact:portMap>
						<ipxact:portMap>
							<ipxact:logicalPort>
								<ipxact:name>W_READY</ipxact:name>
							</ipxact:logicalPort>
							<ipxact:physicalPort>
								<ipxact:name>icn_w_ready_out</ipxact:name>
							</ipxact:physicalPort>
							<ipxact:isInformative>false</ipxact:isInformative>
						</ipxact:portMap>
						<ipxact:portMap>
							<ipxact:logicalPort>
								<ipxact:name>W_STRB</ipxact:name>
							</ipxact:logicalPort>
							<ipxact:physicalPort>
								<ipxact:name>icn_w_strb_in</ipxact:name>
							</ipxact:physicalPort>
							<ipxact:isInformative>false</ipxact:isInformative>
						</ipxact:portMap>
						<ipxact:portMap>
							<ipxact:logicalPort>
								<ipxact:name>W_VALID</ipxact:name>
							</ipxact:logicalPort>
							<ipxact:physicalPort>
								<ipxact:name>icn_w_valid_in</ipxact:name>
							</ipxact:physicalPort>
							<ipxact:isInformative>false</ipxact:isInformative>
						</ipxact:portMap>
						<ipxact:portMap>
							<ipxact:logicalPort>
								<ipxact:name>AR_READY</ipxact:name>
							</ipxact:logicalPort>
							<ipxact:physicalPort>
								<ipxact:name>icn_ar_ready_out</ipxact:name>
							</ipxact:physicalPort>
							<ipxact:isInformative>false</ipxact:isInformative>
						</ipxact:portMap>
					</ipxact:portMaps>
				</ipxact:abstractionType>
			</ipxact:abstractionTypes>
			<ipxact:target/>
		</ipxact:busInterface>
	</ipxact:busInterfaces>
	<ipxact:addressSpaces>
		<ipxact:addressSpace>
			<ipxact:name>interconnect</ipxact:name>
			<ipxact:range>'h4000</ipxact:range>
			<ipxact:width>32</ipxact:width>
			<ipxact:segments>
				<ipxact:segment>
					<ipxact:name>SS_0</ipxact:name>
					<ipxact:addressOffset>'h0</ipxact:addressOffset>
					<ipxact:range>'h1000</ipxact:range>
				</ipxact:segment>
				<ipxact:segment>
					<ipxact:name>SS_1</ipxact:name>
					<ipxact:addressOffset>'h1000</ipxact:addressOffset>
					<ipxact:range>'h1000</ipxact:range>
				</ipxact:segment>
				<ipxact:segment>
					<ipxact:name>SS_2</ipxact:name>
					<ipxact:addressOffset>'h2000</ipxact:addressOffset>
					<ipxact:range>'h1000</ipxact:range>
				</ipxact:segment>
				<ipxact:segment>
					<ipxact:name>SS_3</ipxact:name>
					<ipxact:addressOffset>'h3000</ipxact:addressOffset>
					<ipxact:range>'h1000</ipxact:range>
				</ipxact:segment>
			</ipxact:segments>
		</ipxact:addressSpace>
	</ipxact:addressSpaces>
	<ipxact:model>
		<ipxact:views>
			<ipxact:view>
				<ipxact:name>flat_verilog</ipxact:name>
				<ipxact:envIdentifier>Verilog:kactus2.cs.tut.fi:</ipxact:envIdentifier>
				<ipxact:componentInstantiationRef>verilog_implementation</ipxact:componentInstantiationRef>
			</ipxact:view>
		</ipxact:views>
		<ipxact:instantiations>
			<ipxact:componentInstantiation>
				<ipxact:name>verilog_implementation</ipxact:name>
				<ipxact:language>Verilog</ipxact:language>
				<ipxact:moduleName>ICN_SS</ipxact:moduleName>
				<ipxact:moduleParameters>
					<ipxact:moduleParameter parameterId="uuid_0d277280_44db_46bc_b869_89618a31fe17" usageType="nontyped">
						<ipxact:name>APB_AW</ipxact:name>
						<ipxact:value>uuid_43badc9f_5035_4aaf_999f_e5eae3b3af1e</ipxact:value>
					</ipxact:moduleParameter>
					<ipxact:moduleParameter parameterId="uuid_3a2e9670_ca7f_4096_8895_646e40e5c34e" usageType="nontyped">
						<ipxact:name>APB_DW</ipxact:name>
						<ipxact:value>uuid_4821f764_9140_40bb_9660_7efce3fe7b59</ipxact:value>
					</ipxact:moduleParameter>
					<ipxact:moduleParameter parameterId="uuid_a473d587_f178_4cba_bc86_787aead97242" usageType="nontyped">
						<ipxact:name>APB_TARGETS</ipxact:name>
						<ipxact:value>uuid_e4622e71_1ded_4bf0_9635_ed555c5f3ba3</ipxact:value>
					</ipxact:moduleParameter>
					<ipxact:moduleParameter parameterId="uuid_7751a5f1_89a9_4023_b49f_ea243be64d30" usageType="nontyped">
						<ipxact:name>AXI4LITE_AW</ipxact:name>
						<ipxact:value>uuid_cd8984e0_82d0_4fd1_865c_89a589d0a092</ipxact:value>
					</ipxact:moduleParameter>
					<ipxact:moduleParameter parameterId="uuid_8f9218d6_ec91_42e2_b5bc_3666f143fe25" usageType="nontyped">
						<ipxact:name>AXI4LITE_DW</ipxact:name>
						<ipxact:value>uuid_0b1ff8e3_2c14_40bf_8689_f80d887b9a0b</ipxact:value>
					</ipxact:moduleParameter>
					<ipxact:moduleParameter parameterId="uuid_b966151f_3304_49aa_b4bf_4a402301073f" usageType="nontyped">
						<ipxact:name>SS_CTRL_W</ipxact:name>
						<ipxact:value>uuid_6e221ea5_430f_4ad7_afdb_a74f5e361823</ipxact:value>
					</ipxact:moduleParameter>
				</ipxact:moduleParameters>
			</ipxact:componentInstantiation>
		</ipxact:instantiations>
		<ipxact:ports>
			<ipxact:port>
				<ipxact:name>clk</ipxact:name>
				<ipxact:wire>
					<ipxact:direction>in</ipxact:direction>
					<ipxact:vectors>
						<ipxact:vector>
							<ipxact:left></ipxact:left>
							<ipxact:right></ipxact:right>
						</ipxact:vector>
					</ipxact:vectors>
					<ipxact:wireTypeDefs>
						<ipxact:wireTypeDef>
							<ipxact:typeName>logic</ipxact:typeName>
						</ipxact:wireTypeDef>
					</ipxact:wireTypeDefs>
					<ipxact:drivers>
						<ipxact:driver>
							<ipxact:defaultValue></ipxact:defaultValue>
						</ipxact:driver>
					</ipxact:drivers>
				</ipxact:wire>
			</ipxact:port>
			<ipxact:port>
				<ipxact:name>reset_int</ipxact:name>
				<ipxact:wire>
					<ipxact:direction>in</ipxact:direction>
					<ipxact:vectors>
						<ipxact:vector>
							<ipxact:left></ipxact:left>
							<ipxact:right></ipxact:right>
						</ipxact:vector>
					</ipxact:vectors>
					<ipxact:wireTypeDefs>
						<ipxact:wireTypeDef>
							<ipxact:typeName>logic</ipxact:typeName>
						</ipxact:wireTypeDef>
					</ipxact:wireTypeDefs>
					<ipxact:drivers>
						<ipxact:driver>
							<ipxact:defaultValue></ipxact:defaultValue>
						</ipxact:driver>
					</ipxact:drivers>
				</ipxact:wire>
			</ipxact:port>
			<ipxact:port>
				<ipxact:name>ss_ctrl_icn</ipxact:name>
				<ipxact:wire>
					<ipxact:direction>in</ipxact:direction>
					<ipxact:vectors>
						<ipxact:vector>
							<ipxact:left>uuid_6e221ea5_430f_4ad7_afdb_a74f5e361823-1</ipxact:left>
							<ipxact:right>0</ipxact:right>
						</ipxact:vector>
					</ipxact:vectors>
					<ipxact:wireTypeDefs>
						<ipxact:wireTypeDef>
							<ipxact:typeName>logic</ipxact:typeName>
						</ipxact:wireTypeDef>
					</ipxact:wireTypeDefs>
					<ipxact:drivers>
						<ipxact:driver>
							<ipxact:defaultValue></ipxact:defaultValue>
						</ipxact:driver>
					</ipxact:drivers>
				</ipxact:wire>
			</ipxact:port>
			<ipxact:port>
				<ipxact:name>PADDR</ipxact:name>
				<ipxact:wire>
					<ipxact:direction>out</ipxact:direction>
					<ipxact:vectors>
						<ipxact:vector>
							<ipxact:left>uuid_43badc9f_5035_4aaf_999f_e5eae3b3af1e-1</ipxact:left>
							<ipxact:right>0</ipxact:right>
						</ipxact:vector>
					</ipxact:vectors>
					<ipxact:wireTypeDefs>
						<ipxact:wireTypeDef>
							<ipxact:typeName>logic</ipxact:typeName>
						</ipxact:wireTypeDef>
					</ipxact:wireTypeDefs>
				</ipxact:wire>
			</ipxact:port>
			<ipxact:port>
				<ipxact:name>PENABLE</ipxact:name>
				<ipxact:wire>
					<ipxact:direction>out</ipxact:direction>
					<ipxact:vectors>
						<ipxact:vector>
							<ipxact:left></ipxact:left>
							<ipxact:right></ipxact:right>
						</ipxact:vector>
					</ipxact:vectors>
					<ipxact:wireTypeDefs>
						<ipxact:wireTypeDef>
							<ipxact:typeName>logic</ipxact:typeName>
						</ipxact:wireTypeDef>
					</ipxact:wireTypeDefs>
				</ipxact:wire>
			</ipxact:port>
			<ipxact:port>
				<ipxact:name>PRDATA</ipxact:name>
				<ipxact:wire>
					<ipxact:direction>in</ipxact:direction>
					<ipxact:vectors>
						<ipxact:vector>
							<ipxact:left>(uuid_4821f764_9140_40bb_9660_7efce3fe7b59*uuid_e4622e71_1ded_4bf0_9635_ed555c5f3ba3)-1</ipxact:left>
							<ipxact:right>0</ipxact:right>
						</ipxact:vector>
					</ipxact:vectors>
					<ipxact:wireTypeDefs>
						<ipxact:wireTypeDef>
							<ipxact:typeName>logic</ipxact:typeName>
						</ipxact:wireTypeDef>
					</ipxact:wireTypeDefs>
				</ipxact:wire>
			</ipxact:port>
			<ipxact:port>
				<ipxact:name>PREADY</ipxact:name>
				<ipxact:wire>
					<ipxact:direction>in</ipxact:direction>
					<ipxact:vectors>
						<ipxact:vector>
							<ipxact:left>uuid_e4622e71_1ded_4bf0_9635_ed555c5f3ba3-1</ipxact:left>
							<ipxact:right>0</ipxact:right>
						</ipxact:vector>
					</ipxact:vectors>
					<ipxact:wireTypeDefs>
						<ipxact:wireTypeDef>
							<ipxact:typeName>logic</ipxact:typeName>
						</ipxact:wireTypeDef>
					</ipxact:wireTypeDefs>
				</ipxact:wire>
			</ipxact:port>
			<ipxact:port>
				<ipxact:name>PSEL</ipxact:name>
				<ipxact:wire>
					<ipxact:direction>out</ipxact:direction>
					<ipxact:vectors>
						<ipxact:vector>
							<ipxact:left>uuid_e4622e71_1ded_4bf0_9635_ed555c5f3ba3-1</ipxact:left>
							<ipxact:right>0</ipxact:right>
						</ipxact:vector>
					</ipxact:vectors>
					<ipxact:wireTypeDefs>
						<ipxact:wireTypeDef>
							<ipxact:typeName>logic</ipxact:typeName>
						</ipxact:wireTypeDef>
					</ipxact:wireTypeDefs>
				</ipxact:wire>
			</ipxact:port>
			<ipxact:port>
				<ipxact:name>PSLVERR</ipxact:name>
				<ipxact:wire>
					<ipxact:direction>in</ipxact:direction>
					<ipxact:vectors>
						<ipxact:vector>
							<ipxact:left>uuid_e4622e71_1ded_4bf0_9635_ed555c5f3ba3-1</ipxact:left>
							<ipxact:right>0</ipxact:right>
						</ipxact:vector>
					</ipxact:vectors>
					<ipxact:wireTypeDefs>
						<ipxact:wireTypeDef>
							<ipxact:typeName>logic</ipxact:typeName>
						</ipxact:wireTypeDef>
					</ipxact:wireTypeDefs>
				</ipxact:wire>
			</ipxact:port>
			<ipxact:port>
				<ipxact:name>PWDATA</ipxact:name>
				<ipxact:wire>
					<ipxact:direction>out</ipxact:direction>
					<ipxact:vectors>
						<ipxact:vector>
							<ipxact:left>uuid_4821f764_9140_40bb_9660_7efce3fe7b59-1</ipxact:left>
							<ipxact:right>0</ipxact:right>
						</ipxact:vector>
					</ipxact:vectors>
					<ipxact:wireTypeDefs>
						<ipxact:wireTypeDef>
							<ipxact:typeName>logic</ipxact:typeName>
						</ipxact:wireTypeDef>
					</ipxact:wireTypeDefs>
				</ipxact:wire>
			</ipxact:port>
			<ipxact:port>
				<ipxact:name>PWRITE</ipxact:name>
				<ipxact:wire>
					<ipxact:direction>out</ipxact:direction>
					<ipxact:vectors>
						<ipxact:vector>
							<ipxact:left></ipxact:left>
							<ipxact:right></ipxact:right>
						</ipxact:vector>
					</ipxact:vectors>
					<ipxact:wireTypeDefs>
						<ipxact:wireTypeDef>
							<ipxact:typeName>logic</ipxact:typeName>
						</ipxact:wireTypeDef>
					</ipxact:wireTypeDefs>
				</ipxact:wire>
			</ipxact:port>
			<ipxact:port>
				<ipxact:name>icn_ar_addr_in</ipxact:name>
				<ipxact:wire>
					<ipxact:direction>in</ipxact:direction>
					<ipxact:vectors>
						<ipxact:vector>
							<ipxact:left>uuid_cd8984e0_82d0_4fd1_865c_89a589d0a092-1</ipxact:left>
							<ipxact:right>0</ipxact:right>
						</ipxact:vector>
					</ipxact:vectors>
					<ipxact:wireTypeDefs>
						<ipxact:wireTypeDef>
							<ipxact:typeName>logic</ipxact:typeName>
						</ipxact:wireTypeDef>
					</ipxact:wireTypeDefs>
				</ipxact:wire>
			</ipxact:port>
			<ipxact:port>
				<ipxact:name>icn_ar_valid_in</ipxact:name>
				<ipxact:wire>
					<ipxact:direction>in</ipxact:direction>
					<ipxact:vectors>
						<ipxact:vector>
							<ipxact:left></ipxact:left>
							<ipxact:right></ipxact:right>
						</ipxact:vector>
					</ipxact:vectors>
					<ipxact:wireTypeDefs>
						<ipxact:wireTypeDef>
							<ipxact:typeName>logic</ipxact:typeName>
						</ipxact:wireTypeDef>
					</ipxact:wireTypeDefs>
				</ipxact:wire>
			</ipxact:port>
			<ipxact:port>
				<ipxact:name>icn_aw_addr_in</ipxact:name>
				<ipxact:wire>
					<ipxact:direction>in</ipxact:direction>
					<ipxact:vectors>
						<ipxact:vector>
							<ipxact:left>uuid_cd8984e0_82d0_4fd1_865c_89a589d0a092-1</ipxact:left>
							<ipxact:right>0</ipxact:right>
						</ipxact:vector>
					</ipxact:vectors>
					<ipxact:wireTypeDefs>
						<ipxact:wireTypeDef>
							<ipxact:typeName>logic</ipxact:typeName>
						</ipxact:wireTypeDef>
					</ipxact:wireTypeDefs>
				</ipxact:wire>
			</ipxact:port>
			<ipxact:port>
				<ipxact:name>icn_aw_valid_in</ipxact:name>
				<ipxact:wire>
					<ipxact:direction>in</ipxact:direction>
					<ipxact:vectors>
						<ipxact:vector>
							<ipxact:left></ipxact:left>
							<ipxact:right></ipxact:right>
						</ipxact:vector>
					</ipxact:vectors>
					<ipxact:wireTypeDefs>
						<ipxact:wireTypeDef>
							<ipxact:typeName>logic</ipxact:typeName>
						</ipxact:wireTypeDef>
					</ipxact:wireTypeDefs>
				</ipxact:wire>
			</ipxact:port>
			<ipxact:port>
				<ipxact:name>icn_b_ready_in</ipxact:name>
				<ipxact:wire>
					<ipxact:direction>in</ipxact:direction>
					<ipxact:vectors>
						<ipxact:vector>
							<ipxact:left></ipxact:left>
							<ipxact:right></ipxact:right>
						</ipxact:vector>
					</ipxact:vectors>
					<ipxact:wireTypeDefs>
						<ipxact:wireTypeDef>
							<ipxact:typeName>logic</ipxact:typeName>
						</ipxact:wireTypeDef>
					</ipxact:wireTypeDefs>
				</ipxact:wire>
			</ipxact:port>
			<ipxact:port>
				<ipxact:name>icn_r_ready_in</ipxact:name>
				<ipxact:wire>
					<ipxact:direction>in</ipxact:direction>
					<ipxact:vectors>
						<ipxact:vector>
							<ipxact:left></ipxact:left>
							<ipxact:right></ipxact:right>
						</ipxact:vector>
					</ipxact:vectors>
					<ipxact:wireTypeDefs>
						<ipxact:wireTypeDef>
							<ipxact:typeName>logic</ipxact:typeName>
						</ipxact:wireTypeDef>
					</ipxact:wireTypeDefs>
				</ipxact:wire>
			</ipxact:port>
			<ipxact:port>
				<ipxact:name>icn_w_data_in</ipxact:name>
				<ipxact:wire>
					<ipxact:direction>in</ipxact:direction>
					<ipxact:vectors>
						<ipxact:vector>
							<ipxact:left>uuid_0b1ff8e3_2c14_40bf_8689_f80d887b9a0b-1</ipxact:left>
							<ipxact:right>0</ipxact:right>
						</ipxact:vector>
					</ipxact:vectors>
					<ipxact:wireTypeDefs>
						<ipxact:wireTypeDef>
							<ipxact:typeName>logic</ipxact:typeName>
						</ipxact:wireTypeDef>
					</ipxact:wireTypeDefs>
				</ipxact:wire>
			</ipxact:port>
			<ipxact:port>
				<ipxact:name>icn_w_strb_in</ipxact:name>
				<ipxact:wire>
					<ipxact:direction>in</ipxact:direction>
					<ipxact:vectors>
						<ipxact:vector>
							<ipxact:left>(uuid_0b1ff8e3_2c14_40bf_8689_f80d887b9a0b/8)-1</ipxact:left>
							<ipxact:right>0</ipxact:right>
						</ipxact:vector>
					</ipxact:vectors>
					<ipxact:wireTypeDefs>
						<ipxact:wireTypeDef>
							<ipxact:typeName>logic</ipxact:typeName>
						</ipxact:wireTypeDef>
					</ipxact:wireTypeDefs>
				</ipxact:wire>
			</ipxact:port>
			<ipxact:port>
				<ipxact:name>icn_w_valid_in</ipxact:name>
				<ipxact:wire>
					<ipxact:direction>in</ipxact:direction>
					<ipxact:vectors>
						<ipxact:vector>
							<ipxact:left></ipxact:left>
							<ipxact:right></ipxact:right>
						</ipxact:vector>
					</ipxact:vectors>
					<ipxact:wireTypeDefs>
						<ipxact:wireTypeDef>
							<ipxact:typeName>logic</ipxact:typeName>
						</ipxact:wireTypeDef>
					</ipxact:wireTypeDefs>
				</ipxact:wire>
			</ipxact:port>
			<ipxact:port>
				<ipxact:name>icn_ar_ready_out</ipxact:name>
				<ipxact:wire>
					<ipxact:direction>out</ipxact:direction>
					<ipxact:vectors>
						<ipxact:vector>
							<ipxact:left></ipxact:left>
							<ipxact:right></ipxact:right>
						</ipxact:vector>
					</ipxact:vectors>
					<ipxact:wireTypeDefs>
						<ipxact:wireTypeDef>
							<ipxact:typeName>logic</ipxact:typeName>
						</ipxact:wireTypeDef>
					</ipxact:wireTypeDefs>
				</ipxact:wire>
			</ipxact:port>
			<ipxact:port>
				<ipxact:name>icn_aw_ready_out</ipxact:name>
				<ipxact:wire>
					<ipxact:direction>out</ipxact:direction>
					<ipxact:vectors>
						<ipxact:vector>
							<ipxact:left></ipxact:left>
							<ipxact:right></ipxact:right>
						</ipxact:vector>
					</ipxact:vectors>
					<ipxact:wireTypeDefs>
						<ipxact:wireTypeDef>
							<ipxact:typeName>logic</ipxact:typeName>
						</ipxact:wireTypeDef>
					</ipxact:wireTypeDefs>
				</ipxact:wire>
			</ipxact:port>
			<ipxact:port>
				<ipxact:name>icn_b_resp_out</ipxact:name>
				<ipxact:wire>
					<ipxact:direction>out</ipxact:direction>
					<ipxact:vectors>
						<ipxact:vector>
							<ipxact:left>1</ipxact:left>
							<ipxact:right>0</ipxact:right>
						</ipxact:vector>
					</ipxact:vectors>
					<ipxact:wireTypeDefs>
						<ipxact:wireTypeDef>
							<ipxact:typeName>logic</ipxact:typeName>
						</ipxact:wireTypeDef>
					</ipxact:wireTypeDefs>
				</ipxact:wire>
			</ipxact:port>
			<ipxact:port>
				<ipxact:name>icn_b_valid_out</ipxact:name>
				<ipxact:wire>
					<ipxact:direction>out</ipxact:direction>
					<ipxact:vectors>
						<ipxact:vector>
							<ipxact:left></ipxact:left>
							<ipxact:right></ipxact:right>
						</ipxact:vector>
					</ipxact:vectors>
					<ipxact:wireTypeDefs>
						<ipxact:wireTypeDef>
							<ipxact:typeName>logic</ipxact:typeName>
						</ipxact:wireTypeDef>
					</ipxact:wireTypeDefs>
				</ipxact:wire>
			</ipxact:port>
			<ipxact:port>
				<ipxact:name>icn_r_data_out</ipxact:name>
				<ipxact:wire>
					<ipxact:direction>out</ipxact:direction>
					<ipxact:vectors>
						<ipxact:vector>
							<ipxact:left>uuid_0b1ff8e3_2c14_40bf_8689_f80d887b9a0b-1</ipxact:left>
							<ipxact:right>0</ipxact:right>
						</ipxact:vector>
					</ipxact:vectors>
					<ipxact:wireTypeDefs>
						<ipxact:wireTypeDef>
							<ipxact:typeName>logic</ipxact:typeName>
						</ipxact:wireTypeDef>
					</ipxact:wireTypeDefs>
				</ipxact:wire>
			</ipxact:port>
			<ipxact:port>
				<ipxact:name>icn_r_resp_out</ipxact:name>
				<ipxact:wire>
					<ipxact:direction>out</ipxact:direction>
					<ipxact:vectors>
						<ipxact:vector>
							<ipxact:left>1</ipxact:left>
							<ipxact:right>0</ipxact:right>
						</ipxact:vector>
					</ipxact:vectors>
					<ipxact:wireTypeDefs>
						<ipxact:wireTypeDef>
							<ipxact:typeName>logic</ipxact:typeName>
						</ipxact:wireTypeDef>
					</ipxact:wireTypeDefs>
				</ipxact:wire>
			</ipxact:port>
			<ipxact:port>
				<ipxact:name>icn_r_valid_out</ipxact:name>
				<ipxact:wire>
					<ipxact:direction>out</ipxact:direction>
					<ipxact:vectors>
						<ipxact:vector>
							<ipxact:left></ipxact:left>
							<ipxact:right></ipxact:right>
						</ipxact:vector>
					</ipxact:vectors>
					<ipxact:wireTypeDefs>
						<ipxact:wireTypeDef>
							<ipxact:typeName>logic</ipxact:typeName>
						</ipxact:wireTypeDef>
					</ipxact:wireTypeDefs>
				</ipxact:wire>
			</ipxact:port>
			<ipxact:port>
				<ipxact:name>icn_w_ready_out</ipxact:name>
				<ipxact:wire>
					<ipxact:direction>out</ipxact:direction>
					<ipxact:vectors>
						<ipxact:vector>
							<ipxact:left></ipxact:left>
							<ipxact:right></ipxact:right>
						</ipxact:vector>
					</ipxact:vectors>
					<ipxact:wireTypeDefs>
						<ipxact:wireTypeDef>
							<ipxact:typeName>logic</ipxact:typeName>
						</ipxact:wireTypeDef>
					</ipxact:wireTypeDefs>
				</ipxact:wire>
			</ipxact:port>
		</ipxact:ports>
	</ipxact:model>
	<ipxact:fileSets>
		<ipxact:fileSet>
			<ipxact:name>rtl</ipxact:name>
			<ipxact:group>generatedFiles</ipxact:group>
			<ipxact:file>
				<ipxact:name>../../../../../src/rtl/ICN_SS.sv</ipxact:name>
				<ipxact:fileType>verilogSource</ipxact:fileType>
				<ipxact:description>Generated at 15:01:14 on 19.02.2024 by Kactus2. </ipxact:description>
				<ipxact:vendorExtensions>
					<kactus2:hash>e6be36081940437c604c2be2dd867fe39a743636</kactus2:hash>
				</ipxact:vendorExtensions>
			</ipxact:file>
		</ipxact:fileSet>
	</ipxact:fileSets>
	<ipxact:parameters>
		<ipxact:parameter kactus2:usageCount="13" parameterId="uuid_e4622e71_1ded_4bf0_9635_ed555c5f3ba3" resolve="immediate">
			<ipxact:name>APB_TARGETS</ipxact:name>
			<ipxact:value>4</ipxact:value>
		</ipxact:parameter>
		<ipxact:parameter kactus2:usageCount="8" parameterId="uuid_4821f764_9140_40bb_9660_7efce3fe7b59" resolve="user">
			<ipxact:name>APB_DW</ipxact:name>
			<ipxact:value>32</ipxact:value>
		</ipxact:parameter>
		<ipxact:parameter kactus2:usageCount="5" parameterId="uuid_43badc9f_5035_4aaf_999f_e5eae3b3af1e" resolve="user">
			<ipxact:name>APB_AW</ipxact:name>
			<ipxact:value>32</ipxact:value>
		</ipxact:parameter>
		<ipxact:parameter kactus2:usageCount="4" parameterId="uuid_6e221ea5_430f_4ad7_afdb_a74f5e361823" resolve="user">
			<ipxact:name>SS_CTRL_W</ipxact:name>
			<ipxact:value>8</ipxact:value>
		</ipxact:parameter>
		<ipxact:parameter kactus2:usageCount="3" parameterId="uuid_cd8984e0_82d0_4fd1_865c_89a589d0a092">
			<ipxact:name>AXI4LITE_AW</ipxact:name>
			<ipxact:value>32</ipxact:value>
		</ipxact:parameter>
		<ipxact:parameter kactus2:usageCount="4" parameterId="uuid_0b1ff8e3_2c14_40bf_8689_f80d887b9a0b">
			<ipxact:name>AXI4LITE_DW</ipxact:name>
			<ipxact:value>32</ipxact:value>
		</ipxact:parameter>
	</ipxact:parameters>
	<ipxact:vendorExtensions>
		<kactus2:fileDependencies>
			<kactus2:fileDependency manual="false" bidirectional="false" locked="false">
				<kactus2:fileRef1>../../../../../src/rtl/ICN_SS.sv</kactus2:fileRef1>
				<kactus2:fileRef2>$External$/verification/verilator/src/hdl/nms/ICN_SS.sv</kactus2:fileRef2>
				<ipxact:description>Include reference to verification/verilator/src/hdl/nms/ICN_SS.sv</ipxact:description>
			</kactus2:fileDependency>
			<kactus2:fileDependency manual="false" bidirectional="false" locked="false">
				<kactus2:fileRef1>../../../../../src/rtl/ICN_SS.sv</kactus2:fileRef1>
				<kactus2:fileRef2>$External$/verification/verilator/src/hdl/ms/ICN_SS.sv</kactus2:fileRef2>
				<ipxact:description>Include reference to verification/verilator/src/hdl/ms/ICN_SS.sv</ipxact:description>
			</kactus2:fileDependency>
			<kactus2:fileDependency manual="false" bidirectional="false" locked="false">
				<kactus2:fileRef1>../../../../../src/rtl/ICN_SS.sv</kactus2:fileRef1>
				<kactus2:fileRef2>$External$/axi_lite_to_apb_intf.sv</kactus2:fileRef2>
				<ipxact:description>Submodule instantiation of module axi_lite_to_apb_intf</ipxact:description>
			</kactus2:fileDependency>
		</kactus2:fileDependencies>
		<kactus2:kts_attributes>
			<kactus2:kts_productHier>IP</kactus2:kts_productHier>
			<kactus2:kts_implementation>HW</kactus2:kts_implementation>
			<kactus2:kts_firmness>Mutable</kactus2:kts_firmness>
		</kactus2:kts_attributes>
	</ipxact:vendorExtensions>
</ipxact:component>
